{"is_source_file": true, "format": "TypeScript", "description": "This file is an index file (index.tsx) in a React project's frontend code, typically used as an entry point or aggregator for module exports.", "external_files": [], "external_methods": [], "published": [], "classes": [], "methods": [], "calls": [], "search-terms": ["index.tsx", "React", "TypeScript", "frontend", "aggregation", "entry point"], "state": 2, "file_id": 22, "knowledge_revision": 46, "git_revision": "15817a1f1855c1d4bb8de2743d3c874dde5ab86f", "ctags": [], "hash": "4549acc5d31ac1a7faa23ed63a73ce80", "format-version": 4, "code-base-name": "hey_frontend", "filename": "hey_frontend/src/index.tsx", "revision_history": [{"46": "15817a1f1855c1d4bb8de2743d3c874dde5ab86f"}]}